{
  "$schema": "https://developer.microsoft.com/json-schemas/fabric/item/report/definition/visualContainer/2.8.0/schema.json",
  "name": "a722fceb2c3d4e5f6072",
  "position": {
    "x": 751,
    "y": 150,
    "z": 8702,
    "height": 179,
    "width": 515,
    "tabOrder": 8702
  },
  "visual": {
    "visualType": "clusteredBarChart",
    "query": {
      "queryState": {
        "Category": {
          "projections": [
            {
              "field": {
                "Column": {
                  "Expression": {
                    "SourceRef": {
                      "Entity": "Training"
                    }
                  },
                  "Property": "Department"
                }
              },
              "queryRef": "Training.Department",
              "nativeQueryRef": "Department",
              "active": true
            }
          ]
        },
        "Y": {
          "projections": [
            {
              "field": {
                "Measure": {
                  "Expression": {
                    "SourceRef": {
                      "Entity": "_Measures"
                    }
                  },
                  "Property": "Training Hours per Employee"
                }
              },
              "queryRef": "_Measures.Training Hours per Employee",
              "nativeQueryRef": "Training Hours per Employee"
            }
          ]
        }
      },
      "sortDefinition": {
        "sort": [
          {
            "field": {
              "Measure": {
                "Expression": {
                  "SourceRef": {
                    "Entity": "_Measures"
                  }
                },
                "Property": "Training Hours per Employee"
              }
            },
            "direction": "Descending"
          }
        ],
        "isDefaultSort": true
      }
    },
    "objects": {
      "labels": [
        {
          "properties": {
            "show": {
              "expr": {
                "Literal": {
                  "Value": "true"
                }
              }
            }
          }
        }
      ],
      "dataPoint": [
        {
          "properties": {
            "defaultColor": {
              "solid": {
                "color": {
                  "expr": {
                    "Literal": {
                      "Value": "'#2E75B6'"
                    }
                  }
                }
              }
            }
          }
        }
      ]
    },
    "visualContainerObjects": {
      "title": [
        {
          "properties": {
            "text": {
              "expr": {
                "Literal": {
                  "Value": "'Hours per employee by department'"
                }
              }
            }
          }
        }
      ]
    },
    "drillFilterOtherVisuals": true
  }
}