{
  "$schema": "https://developer.microsoft.com/json-schemas/fabric/item/report/definition/visualContainer/2.8.0/schema.json",
  "name": "c26d500a2b3c4d5e6f05",
  "position": {
    "x": 926,
    "y": 437,
    "z": 11000,
    "height": 275,
    "width": 338,
    "tabOrder": 11000
  },
  "visual": {
    "visualType": "donutChart",
    "query": {
      "queryState": {
        "Category": {
          "projections": [
            {
              "field": {
                "Column": {
                  "Expression": {
                    "SourceRef": {
                      "Entity": "Employees"
                    }
                  },
                  "Property": "EmploymentType"
                }
              },
              "queryRef": "Employees.EmploymentType",
              "nativeQueryRef": "EmploymentType",
              "active": true
            }
          ]
        },
        "Y": {
          "projections": [
            {
              "field": {
                "Measure": {
                  "Expression": {
                    "SourceRef": {
                      "Entity": "_Measures"
                    }
                  },
                  "Property": "Active Headcount"
                }
              },
              "queryRef": "_Measures.Active Headcount",
              "nativeQueryRef": "Active Headcount"
            }
          ]
        }
      }
    },
    "objects": {
      "labels": [
        {
          "properties": {
            "show": {
              "expr": {
                "Literal": {
                  "Value": "true"
                }
              }
            }
          }
        }
      ],
      "dataPoint": [
        {
          "properties": {
            "fill": {
              "solid": {
                "color": {
                  "expr": {
                    "Literal": {
                      "Value": "'#1F3864'"
                    }
                  }
                }
              }
            }
          },
          "selector": {
            "data": [
              {
                "scopeId": {
                  "Comparison": {
                    "ComparisonKind": 0,
                    "Left": {
                      "Column": {
                        "Expression": {
                          "SourceRef": {
                            "Entity": "Employees"
                          }
                        },
                        "Property": "EmploymentType"
                      }
                    },
                    "Right": {
                      "Literal": {
                        "Value": "'Permanent'"
                      }
                    }
                  }
                }
              }
            ]
          }
        },
        {
          "properties": {
            "fill": {
              "solid": {
                "color": {
                  "expr": {
                    "Literal": {
                      "Value": "'#C55A11'"
                    }
                  }
                }
              }
            }
          },
          "selector": {
            "data": [
              {
                "scopeId": {
                  "Comparison": {
                    "ComparisonKind": 0,
                    "Left": {
                      "Column": {
                        "Expression": {
                          "SourceRef": {
                            "Entity": "Employees"
                          }
                        },
                        "Property": "EmploymentType"
                      }
                    },
                    "Right": {
                      "Literal": {
                        "Value": "'Contract'"
                      }
                    }
                  }
                }
              }
            ]
          }
        },
        {
          "properties": {
            "fill": {
              "solid": {
                "color": {
                  "expr": {
                    "Literal": {
                      "Value": "'#7F7F7F'"
                    }
                  }
                }
              }
            }
          },
          "selector": {
            "data": [
              {
                "scopeId": {
                  "Comparison": {
                    "ComparisonKind": 0,
                    "Left": {
                      "Column": {
                        "Expression": {
                          "SourceRef": {
                            "Entity": "Employees"
                          }
                        },
                        "Property": "EmploymentType"
                      }
                    },
                    "Right": {
                      "Literal": {
                        "Value": "'Internship'"
                      }
                    }
                  }
                }
              }
            ]
          }
        }
      ]
    },
    "visualContainerObjects": {
      "title": [
        {
          "properties": {
            "text": {
              "expr": {
                "Literal": {
                  "Value": "'Employment type'"
                }
              }
            }
          }
        }
      ]
    },
    "drillFilterOtherVisuals": true
  }
}